dove/__init__.py
dove/dove.py
dove/tests/__init__.py
dove/tests/test_dove.py
droplet_dove-0.0.3.dist-info/METADATA
droplet_dove-0.0.3.dist-info/RECORD
droplet_dove-0.0.3.dist-info/WHEEL
droplet_dove-0.0.3.dist-info/entry_points.txt
droplet_dove-0.0.3.dist-info/top_level.txt
