Metadata-Version: 2.1
Name: droplet-dove
Version: 0.0.3
Summary: A utility to manage a development server on digital ocean
Home-page: https://github.com/vishalkuo/dove
Author: Vishal Kuo
Author-email: vishalkuo@gmail.com
License: UNKNOWN
Platform: UNKNOWN
Classifier: Programming Language :: Python :: 3.6
Classifier: License :: OSI Approved :: MIT License
Classifier: Operating System :: OS Independent
Requires-Dist: python-digitalocean
Requires-Dist: click
